tasker_bot/__init__.py
tasker_bot-0.0.2.data/scripts/tasker
tasker_bot-0.0.2.dist-info/LICENSE
tasker_bot-0.0.2.dist-info/METADATA
tasker_bot-0.0.2.dist-info/WHEEL
tasker_bot-0.0.2.dist-info/top_level.txt
tasker_bot-0.0.2.dist-info/RECORD
